[
    {
        "title": "Juventus - Inter Milan",
        "embed": "<div style='width:75%;height:0px;position:relative;padding-bottom:56.250%;'><iframe src='https:\/\/www.scorebat.com\/embed\/v\/5e6578c94bdc7\/?s=2' frameborder='0' width='100%' height='100%' allowfullscreen allow='autoplay; fullscreen' style='width:100%;height:100%;position:absolute;left:0px;top:0px;overflow:hidden;'><\/iframe><\/div>",
        "url": "https:\/\/www.scorebat.com\/inter-milan-vs-juventus-live-stream\/",
        "thumbnail": "https:\/\/www.scorebat.com\/og\/m\/og865715.jpeg",
        "date": "2020-03-08T19:45:00+0000",
        "id": 1,
        "side1": {
            "name": "Juventus",
            "url": "https:\/\/www.scorebat.com\/live-stream\/juventus\/"
        },
        "side2": {
            "name": "Inter Milan",
            "url": "https:\/\/www.scorebat.com\/live-stream\/inter-milan\/"
        },
        "competition": {
            "name": "ITALY: Serie A",
            "id": 13,
            "url": "https:\/\/www.scorebat.com\/italy-serie-a-live-scores\/"
        },
        "videos": [
            {
                "title": "Highlights",
                "embed": "<div style='width:100%;height:0px;position:relative;padding-bottom:56.250%;'><iframe src='https:\/\/www.scorebat.com\/embed\/v\/5e6578c94bdc7\/?s=2' frameborder='0' width='50%' height='50%' allowfullscreen allow='autoplay; fullscreen' style='width:50%;height:50%;position:absolute;left:0px;top:0px;overflow:hidden;'><\/iframe><\/div>"
            }
        ]
    },
    {
        "title": "Manchester United - Manchester City",
        "embed": "<div style='width:75%;height:0px;position:relative;padding-bottom:56.250%;'><iframe src='https:\/\/www.scorebat.com\/embed\/v\/5e656e798709e\/?s=2' frameborder='0' width='100%' height='100%' allowfullscreen allow='autoplay; fullscreen' style='width:100%;height:100%;position:absolute;left:0px;top:0px;overflow:hidden;'><\/iframe><\/div>",
        "url": "https:\/\/www.scorebat.com\/manchester-city-vs-manchester-united-live-stream\/",
        "thumbnail": "https:\/\/www.scorebat.com\/og\/m\/og821136.jpeg",
        "date": "2020-03-08T16:30:00+0000",
        "id": 2,
        "side1": {
            "name": "Manchester United",
            "url": "https:\/\/www.scorebat.com\/live-stream\/manchester-united\/"
        },
        "side2": {
            "name": "Manchester City",
            "url": "https:\/\/www.scorebat.com\/live-stream\/manchester-city\/"
        },
        "competition": {
            "name": "ENGLAND: Premier League",
            "id": 15,
            "url": "https:\/\/www.scorebat.com\/england-premier-league-live-scores\/"
        },
        "videos": [
            {
                "title": "Highlights",
                "embed": "<div style='width:100%;height:0px;position:relative;padding-bottom:56.250%;'><iframe src='https:\/\/www.scorebat.com\/embed\/v\/5e656e798709e\/?s=2' frameborder='0' width='100%' height='100%' allowfullscreen allow='autoplay; fullscreen' style='width:100%;height:100%;position:absolute;left:0px;top:0px;overflow:hidden;'><\/iframe><\/div>"
            }
        ]
    },
    {
        "title": "Chelsea - Everton",
        "embed": "<div style='width:75%;height:0px;position:relative;padding-bottom:56.250%;'><iframe src='https:\/\/www.scorebat.com\/embed\/v\/5e6735bd85a97\/?s=2' frameborder='0' width='100%' height='100%' allowfullscreen allow='autoplay; fullscreen' style='width:100%;height:100%;position:absolute;left:0px;top:0px;overflow:hidden;'><\/iframe><\/div>",
        "url": "https:\/\/www.scorebat.com\/chelsea-vs-everton-live-stream\/",
        "thumbnail": "https:\/\/www.scorebat.com\/og\/m\/og821132.jpeg",
        "date": "2020-03-08T14:00:00+0000",
        "id": 3,
        "side1": {
            "name": "Chelsea",
            "url": "https:\/\/www.scorebat.com\/live-stream\/chelsea\/"
        },
        "side2": {
            "name": "Everton",
            "url": "https:\/\/www.scorebat.com\/live-stream\/everton\/"
        },
        "competition": {
            "name": "ENGLAND: Premier League",
            "id": 15,
            "url": "https:\/\/www.scorebat.com\/england-premier-league-live-scores\/"
        },
        "videos": [
            {
                "title": "Extended highlights",
                "embed": "<div style='width:100%;height:0px;position:relative;padding-bottom:56.250%;'><iframe src='https:\/\/www.scorebat.com\/embed\/v\/5e6735bd85a97\/?s=2' frameborder='0' width='100%' height='100%' allowfullscreen allow='autoplay; fullscreen' style='width:100%;height:100%;position:absolute;left:0px;top:0px;overflow:hidden;'><\/iframe><\/div>"
            },
            {
                "title": "Highlights",
                "embed": "<div style='width:100%;height:0px;position:relative;padding-bottom:56.250%;'><iframe src='https:\/\/www.scorebat.com\/embed\/v\/5e656e6eb244f\/?s=2' frameborder='0' width='100%' height='100%' allowfullscreen allow='autoplay; fullscreen' style='width:100%;height:100%;position:absolute;left:0px;top:0px;overflow:hidden;'><\/iframe><\/div>"
            }
        ]
    },
    {
        "title": "AC Milan - Genoa",
        "embed": "<div style='width:75%;height:0px;position:relative;padding-bottom:56.250%;'><iframe src='https:\/\/www.scorebat.com\/embed\/v\/5e652635a627c\/?s=2' frameborder='0' width='100%' height='100%' allowfullscreen allow='autoplay; fullscreen' style='width:100%;height:100%;position:absolute;left:0px;top:0px;overflow:hidden;'><\/iframe><\/div>",
        "url": "https:\/\/www.scorebat.com\/ac-milan-vs-genoa-live-stream\/",
        "thumbnail": "https:\/\/www.scorebat.com\/og\/m\/og865713.jpeg",
        "date": "2020-03-08T14:00:00+0000",
        "id": 5,
        "side1": {
            "name": "AC Milan",
            "url": "https:\/\/www.scorebat.com\/live-stream\/ac-milan\/"
        },
        "side2": {
            "name": "Genoa",
            "url": "https:\/\/www.scorebat.com\/live-stream\/genoa\/"
        },
        "competition": {
            "name": "ITALY: Serie A",
            "id": 13,
            "url": "https:\/\/www.scorebat.com\/italy-serie-a-live-scores\/"
        },
        "videos": [
            {
                "title": "Highlights",
                "embed": "<div style='width:100%;height:0px;position:relative;padding-bottom:56.250%;'><iframe src='https:\/\/www.scorebat.com\/embed\/v\/5e652635a627c\/?s=2' frameborder='0' width='100%' height='100%' allowfullscreen allow='autoplay; fullscreen' style='width:100%;height:100%;position:absolute;left:0px;top:0px;overflow:hidden;'><\/iframe><\/div>"
            }
        ]
    },
    {
        "title": "Burnley - Tottenham Hotspur",
        "embed": "<div style='width:75%;height:0px;position:relative;padding-bottom:56.250%;'><iframe src='https:\/\/www.scorebat.com\/embed\/v\/5e6448a996247\/?s=2' frameborder='0' width='100%' height='100%' allowfullscreen allow='autoplay; fullscreen' style='width:100%;height:100%;position:absolute;left:0px;top:0px;overflow:hidden;'><\/iframe><\/div>",
        "url": "https:\/\/www.scorebat.com\/burnley-vs-tottenham-hotspur-live-stream\/",
        "thumbnail": "https:\/\/www.scorebat.com\/og\/m\/og821131.jpeg",
        "date": "2020-03-07T17:30:00+0000",
        "id": 6,
        "side1": {
            "name": "Burnley",
            "url": "https:\/\/www.scorebat.com\/live-stream\/burnley\/"
        },
        "side2": {
            "name": "Tottenham Hotspur",
            "url": "https:\/\/www.scorebat.com\/live-stream\/tottenham-hotspur\/"
        },
        "competition": {
            "name": "ENGLAND: Premier League",
            "id": 15,
            "url": "https:\/\/www.scorebat.com\/england-premier-league-live-scores\/"
        },
        "videos": [
            {
                "title": "Highlights",
                "embed": "<div style='width:100%;height:0px;position:relative;padding-bottom:56.250%;'><iframe src='https:\/\/www.scorebat.com\/embed\/v\/5e6448a996247\/?s=2' frameborder='0' width='100%' height='100%' allowfullscreen allow='autoplay; fullscreen' style='width:100%;height:100%;position:absolute;left:0px;top:0px;overflow:hidden;'><\/iframe><\/div>"
            }
        ]
    },
    {
        "title": "Arsenal - West Ham United",
        "embed": "<div style='width:75%;height:0px;position:relative;padding-bottom:56.250%;'><iframe src='https:\/\/www.scorebat.com\/embed\/v\/5e6448140a2df\/?s=2' frameborder='0' width='100%' height='100%' allowfullscreen allow='autoplay; fullscreen' style='width:100%;height:100%;position:absolute;left:0px;top:0px;overflow:hidden;'><\/iframe><\/div>",
        "url": "https:\/\/www.scorebat.com\/arsenal-vs-west-ham-united-live-stream\/",
        "thumbnail": "https:\/\/www.scorebat.com\/og\/m\/og821130.jpeg",
        "date": "2020-03-07T15:00:00+0000",
        "id": 7,
        "side1": {
            "name": "Arsenal",
            "url": "https:\/\/www.scorebat.com\/live-stream\/arsenal\/"
        },
        "side2": {
            "name": "West Ham United",
            "url": "https:\/\/www.scorebat.com\/live-stream\/west-ham-united\/"
        },
        "competition": {
            "name": "ENGLAND: Premier League",
            "id": 15,
            "url": "https:\/\/www.scorebat.com\/england-premier-league-live-scores\/"
        },
        "videos": [
            {
                "title": "Highlights",
                "embed": "<div style='width:100%;height:0px;position:relative;padding-bottom:56.250%;'><iframe src='https:\/\/www.scorebat.com\/embed\/v\/5e6448140a2df\/?s=2' frameborder='0' width='100%' height='100%' allowfullscreen allow='autoplay; fullscreen' style='width:100%;height:100%;position:absolute;left:0px;top:0px;overflow:hidden;'><\/iframe><\/div>"
            }
        ]
    },
    {
        "title": "Liverpool - Bournemouth",
        "embed": "<div style='width:75%;height:0px;position:relative;padding-bottom:56.250%;'><iframe src='https:\/\/www.scorebat.com\/embed\/v\/5e641f7ccf6c0\/?s=2' frameborder='0' width='100%' height='100%' allowfullscreen allow='autoplay; fullscreen' style='width:100%;height:100%;position:absolute;left:0px;top:0px;overflow:hidden;'><\/iframe><\/div>",
        "url": "https:\/\/www.scorebat.com\/bournemouth-vs-liverpool-live-stream\/",
        "thumbnail": "https:\/\/www.scorebat.com\/og\/m\/og821135.jpeg",
        "date": "2020-03-07T12:30:00+0000",
        "id": 9,
        "side1": {
            "name": "Liverpool",
            "url": "https:\/\/www.scorebat.com\/live-stream\/liverpool\/"
        },
        "side2": {
            "name": "Bournemouth",
            "url": "https:\/\/www.scorebat.com\/live-stream\/bournemouth\/"
        },
        "competition": {
            "name": "ENGLAND: Premier League",
            "id": 15,
            "url": "https:\/\/www.scorebat.com\/england-premier-league-live-scores\/"
        },
        "videos": [
            {
                "title": "Highlights",
                "embed": "<div style='width:100%;height:0px;position:relative;padding-bottom:56.250%;'><iframe src='https:\/\/www.scorebat.com\/embed\/v\/5e641f7ccf6c0\/?s=2' frameborder='0' width='100%' height='100%' allowfullscreen allow='autoplay; fullscreen' style='width:100%;height:100%;position:absolute;left:0px;top:0px;overflow:hidden;'><\/iframe><\/div>"
            }
        ]
    },
    {
        "title": "Derby County - Manchester United",
        "embed": "<div style='width:75%;height:0px;position:relative;padding-bottom:56.250%;'><iframe src='https:\/\/www.scorebat.com\/embed\/v\/5e625e2b57938\/?s=2' frameborder='0' width='100%' height='100%' allowfullscreen allow='autoplay; fullscreen' style='width:100%;height:100%;position:absolute;left:0px;top:0px;overflow:hidden;'><\/iframe><\/div>",
        "url": "https:\/\/www.scorebat.com\/derby-county-vs-manchester-united-live-stream\/",
        "thumbnail": "https:\/\/www.scorebat.com\/og\/m\/og919454.jpeg",
        "date": "2020-03-05T19:45:00+0000",
        "id": 11,
        "side1": {
            "name": "Derby County",
            "url": "https:\/\/www.scorebat.com\/live-stream\/derby-county\/"
        },
        "side2": {
            "name": "Manchester United",
            "url": "https:\/\/www.scorebat.com\/live-stream\/manchester-united\/"
        },
        "competition": {
            "name": "ENGLAND: FA Cup",
            "id": 76,
            "url": "https:\/\/www.scorebat.com\/england-fa-cup-live-scores\/"
        },
        "videos": [
            {
                "title": "Highlights",
                "embed": "<div style='width:100%;height:0px;position:relative;padding-bottom:56.250%;'><iframe src='https:\/\/www.scorebat.com\/embed\/v\/5e625e2b57938\/?s=2' frameborder='0' width='100%' height='100%' allowfullscreen allow='autoplay; fullscreen' style='width:100%;height:100%;position:absolute;left:0px;top:0px;overflow:hidden;'><\/iframe><\/div>"
            },
            {
                "title": "Highlights",
                "embed": "<div style='width:100%;height:0px;position:relative;padding-bottom:56.250%;'><iframe src='https:\/\/www.scorebat.com\/embed\/v\/5e61ae52cfbbc\/?s=2' frameborder='0' width='100%' height='100%' allowfullscreen allow='autoplay; fullscreen' style='width:100%;height:100%;position:absolute;left:0px;top:0px;overflow:hidden;'><\/iframe><\/div>"
            }
        ]
    },
    {
        "title": "Sheffield Wednesday - Manchester City",
        "embed": "<div style='width:75%;height:0px;position:relative;padding-bottom:56.250%;'><iframe src='https:\/\/www.scorebat.com\/embed\/v\/5e6115cb2134e\/?s=2' frameborder='0' width='100%' height='100%' allowfullscreen allow='autoplay; fullscreen' style='width:100%;height:100%;position:absolute;left:0px;top:0px;overflow:hidden;'><\/iframe><\/div>",
        "url": "https:\/\/www.scorebat.com\/manchester-city-vs-sheffield-wednesday-live-stream\/",
        "thumbnail": "https:\/\/www.scorebat.com\/og\/m\/og919452.jpeg",
        "date": "2020-03-04T19:45:00+0000",
        "id": 12,
        "side1": {
            "name": "Sheffield Wednesday",
            "url": "https:\/\/www.scorebat.com\/live-stream\/sheffield-wednesday\/"
        },
        "side2": {
            "name": "Manchester City",
            "url": "https:\/\/www.scorebat.com\/live-stream\/manchester-city\/"
        },
        "competition": {
            "name": "ENGLAND: FA Cup",
            "id": 76,
            "url": "https:\/\/www.scorebat.com\/england-fa-cup-live-scores\/"
        },
        "videos": [
            {
                "title": "Highlights",
                "embed": "<div style='width:100%;height:0px;position:relative;padding-bottom:56.250%;'><iframe src='https:\/\/www.scorebat.com\/embed\/v\/5e6115cb2134e\/?s=2' frameborder='0' width='100%' height='100%' allowfullscreen allow='autoplay; fullscreen' style='width:100%;height:100%;position:absolute;left:0px;top:0px;overflow:hidden;'><\/iframe><\/div>"
            }
        ]
    },
    {
        "title": "Tottenham Hotspur - Norwich City",
        "embed": "<div style='width:75%;height:0px;position:relative;padding-bottom:56.250%;'><iframe src='https:\/\/www.scorebat.com\/embed\/v\/5e6085c56f3f7\/?s=2' frameborder='0' width='100%' height='100%' allowfullscreen allow='autoplay; fullscreen' style='width:100%;height:100%;position:absolute;left:0px;top:0px;overflow:hidden;'><\/iframe><\/div>",
        "url": "https:\/\/www.scorebat.com\/norwich-city-vs-tottenham-hotspur-live-stream\/",
        "thumbnail": "https:\/\/www.scorebat.com\/og\/m\/og919453.jpeg",
        "date": "2020-03-04T19:45:00+0000",
        "id": 13,
        "side1": {
            "name": "Tottenham Hotspur",
            "url": "https:\/\/www.scorebat.com\/live-stream\/tottenham-hotspur\/"
        },
        "side2": {
            "name": "Norwich City",
            "url": "https:\/\/www.scorebat.com\/live-stream\/norwich-city\/"
        },
        "competition": {
            "name": "ENGLAND: FA Cup",
            "id": 76,
            "url": "https:\/\/www.scorebat.com\/england-fa-cup-live-scores\/"
        },
        "videos": [
            {
                "title": "Highlights",
                "embed": "<div style='width:100%;height:0px;position:relative;padding-bottom:56.250%;'><iframe src='https:\/\/www.scorebat.com\/embed\/v\/5e6085c56f3f7\/?s=2' frameborder='0' width='100%' height='100%' allowfullscreen allow='autoplay; fullscreen' style='width:100%;height:100%;position:absolute;left:0px;top:0px;overflow:hidden;'><\/iframe><\/div>"
            }
        ]
    },
    {
        "title": "Chelsea - Liverpool",
        "embed": "<div style='width:75%;height:0px;position:relative;padding-bottom:56.250%;'><iframe src='https:\/\/www.scorebat.com\/embed\/v\/5e5fa3543ae80\/?s=2' frameborder='0' width='100%' height='100%' allowfullscreen allow='autoplay; fullscreen' style='width:100%;height:100%;position:absolute;left:0px;top:0px;overflow:hidden;'><\/iframe><\/div>",
        "url": "https:\/\/www.scorebat.com\/chelsea-vs-liverpool-live-stream\/",
        "thumbnail": "https:\/\/www.scorebat.com\/og\/m\/og919274.jpeg",
        "date": "2020-03-03T19:45:00+0000",
        "id": 14,
        "side1": {
            "name": "Chelsea",
            "url": "https:\/\/www.scorebat.com\/live-stream\/chelsea\/"
        },
        "side2": {
            "name": "Liverpool",
            "url": "https:\/\/www.scorebat.com\/live-stream\/liverpool\/"
        },
        "competition": {
            "name": "ENGLAND: FA Cup",
            "id": 76,
            "url": "https:\/\/www.scorebat.com\/england-fa-cup-live-scores\/"
        },
        "videos": [
            {
                "title": "Highlights",
                "embed": "<div style='width:100%;height:0px;position:relative;padding-bottom:56.250%;'><iframe src='https:\/\/www.scorebat.com\/embed\/v\/5e5fa3543ae80\/?s=2' frameborder='0' width='100%' height='100%' allowfullscreen allow='autoplay; fullscreen' style='width:100%;height:100%;position:absolute;left:0px;top:0px;overflow:hidden;'><\/iframe><\/div>"
            },
            {
                "title": "Highlights",
                "embed": "<div style='width:100%;height:0px;position:relative;padding-bottom:56.250%;'><iframe src='https:\/\/www.scorebat.com\/embed\/v\/5e5eed4eca407\/?s=2' frameborder='0' width='100%' height='100%' allowfullscreen allow='autoplay; fullscreen' style='width:100%;height:100%;position:absolute;left:0px;top:0px;overflow:hidden;'><\/iframe><\/div>"
            }
        ]
    },
    {
        "title": "Portsmouth - Arsenal",
        "embed": "<div style='width:75%;height:0px;position:relative;padding-bottom:56.250%;'><iframe src='https:\/\/www.scorebat.com\/embed\/v\/5e5d9c5c93038\/?s=2' frameborder='0' width='100%' height='100%' allowfullscreen allow='autoplay; fullscreen' style='width:100%;height:100%;position:absolute;left:0px;top:0px;overflow:hidden;'><\/iframe><\/div>",
        "url": "https:\/\/www.scorebat.com\/arsenal-vs-portsmouth-live-stream\/",
        "thumbnail": "https:\/\/www.scorebat.com\/og\/m\/og919273.jpeg",
        "date": "2020-03-02T19:45:00+0000",
        "id": 15,
        "side1": {
            "name": "Portsmouth",
            "url": "https:\/\/www.scorebat.com\/live-stream\/portsmouth\/"
        },
        "side2": {
            "name": "Arsenal",
            "url": "https:\/\/www.scorebat.com\/live-stream\/arsenal\/"
        },
        "competition": {
            "name": "ENGLAND: FA Cup",
            "id": 76,
            "url": "https:\/\/www.scorebat.com\/england-fa-cup-live-scores\/"
        },
        "videos": [
            {
                "title": "Highlights",
                "embed": "<div style='width:100%;height:0px;position:relative;padding-bottom:56.250%;'><iframe src='https:\/\/www.scorebat.com\/embed\/v\/5e5d9c5c93038\/?s=2' frameborder='0' width='100%' height='100%' allowfullscreen allow='autoplay; fullscreen' style='width:100%;height:100%;position:absolute;left:0px;top:0px;overflow:hidden;'><\/iframe><\/div>"
            }
        ]
    },
    {
        "title": "Everton - Manchester United",
        "embed": "<div style='width:75%;height:0px;position:relative;padding-bottom:56.250%;'><iframe src='https:\/\/www.scorebat.com\/embed\/v\/5e5df1ead9b0f\/?s=2' frameborder='0' width='100%' height='100%' allowfullscreen allow='autoplay; fullscreen' style='width:100%;height:100%;position:absolute;left:0px;top:0px;overflow:hidden;'><\/iframe><\/div>",
        "url": "https:\/\/www.scorebat.com\/everton-vs-manchester-united-live-stream\/",
        "thumbnail": "https:\/\/www.scorebat.com\/og\/m\/og821123.jpeg",
        "date": "2020-03-01T14:00:00+0000",
        "id": 17,
        "side1": {
            "name": "Everton",
            "url": "https:\/\/www.scorebat.com\/live-stream\/everton\/"
        },
        "side2": {
            "name": "Manchester United",
            "url": "https:\/\/www.scorebat.com\/live-stream\/manchester-united\/"
        },
        "competition": {
            "name": "ENGLAND: Premier League",
            "id": 15,
            "url": "https:\/\/www.scorebat.com\/england-premier-league-live-scores\/"
        },
        "videos": [
            {
                "title": "Extended Highlights",
                "embed": "<div style='width:100%;height:0px;position:relative;padding-bottom:56.250%;'><iframe src='https:\/\/www.scorebat.com\/embed\/v\/5e5df1ead9b0f\/?s=2' frameborder='0' width='100%' height='100%' allowfullscreen allow='autoplay; fullscreen' style='width:100%;height:100%;position:absolute;left:0px;top:0px;overflow:hidden;'><\/iframe><\/div>"
            },
            {
                "title": "Highlights",
                "embed": "<div style='width:100%;height:0px;position:relative;padding-bottom:56.250%;'><iframe src='https:\/\/www.scorebat.com\/embed\/v\/5e5c30fba337c\/?s=2' frameborder='0' width='100%' height='100%' allowfullscreen allow='autoplay; fullscreen' style='width:100%;height:100%;position:absolute;left:0px;top:0px;overflow:hidden;'><\/iframe><\/div>"
            }
        ]
    },
    {
        "title": "Tottenham Hotspur - Wolves",
        "embed": "<div style='width:75%;height:0px;position:relative;padding-bottom:56.250%;'><iframe src='https:\/\/www.scorebat.com\/embed\/v\/5e5df1d50108e\/?s=2' frameborder='0' width='100%' height='100%' allowfullscreen allow='autoplay; fullscreen' style='width:100%;height:100%;position:absolute;left:0px;top:0px;overflow:hidden;'><\/iframe><\/div>",
        "url": "https:\/\/www.scorebat.com\/tottenham-hotspur-vs-wolves-live-stream\/",
        "thumbnail": "https:\/\/www.scorebat.com\/og\/m\/og821127.jpeg",
        "date": "2020-03-01T14:00:00+0000",
        "id": 18,
        "side1": {
            "name": "Tottenham Hotspur",
            "url": "https:\/\/www.scorebat.com\/live-stream\/tottenham-hotspur\/"
        },
        "side2": {
            "name": "Wolves",
            "url": "https:\/\/www.scorebat.com\/live-stream\/wolves\/"
        },
        "competition": {
            "name": "ENGLAND: Premier League",
            "id": 15,
            "url": "https:\/\/www.scorebat.com\/england-premier-league-live-scores\/"
        },
        "videos": [
            {
                "title": "Extended highlights",
                "embed": "<div style='width:100%;height:0px;position:relative;padding-bottom:56.250%;'><iframe src='https:\/\/www.scorebat.com\/embed\/v\/5e5df1d50108e\/?s=2' frameborder='0' width='100%' height='100%' allowfullscreen allow='autoplay; fullscreen' style='width:100%;height:100%;position:absolute;left:0px;top:0px;overflow:hidden;'><\/iframe><\/div>"
            },
            {
                "title": "Highlights",
                "embed": "<div style='width:100%;height:0px;position:relative;padding-bottom:56.250%;'><iframe src='https:\/\/www.scorebat.com\/embed\/v\/5e5c31fc47ba7\/?s=2' frameborder='0' width='100%' height='100%' allowfullscreen allow='autoplay; fullscreen' style='width:100%;height:100%;position:absolute;left:0px;top:0px;overflow:hidden;'><\/iframe><\/div>"
            }
        ]
    },
    {
        "title": "Aston Villa - Manchester City",
        "embed": "<div style='width:75%;height:0px;position:relative;padding-bottom:56.250%;'><iframe src='https:\/\/www.scorebat.com\/embed\/v\/5e5c27b21f86e\/?s=2' frameborder='0' width='100%' height='100%' allowfullscreen allow='autoplay; fullscreen' style='width:100%;height:100%;position:absolute;left:0px;top:0px;overflow:hidden;'><\/iframe><\/div>",
        "url": "https:\/\/www.scorebat.com\/aston-villa-vs-manchester-city-live-stream\/",
        "thumbnail": "https:\/\/www.scorebat.com\/og\/m\/og919269.jpeg",
        "date": "2020-03-01T16:30:00+0000",
        "id": 20,
        "side1": {
            "name": "Aston Villa",
            "url": "https:\/\/www.scorebat.com\/live-stream\/aston-villa\/"
        },
        "side2": {
            "name": "Manchester City",
            "url": "https:\/\/www.scorebat.com\/live-stream\/manchester-city\/"
        },
        "competition": {
            "name": "ENGLAND: League Cup",
            "id": 75,
            "url": "https:\/\/www.scorebat.com\/england-league-cup-live-scores\/"
        },
        "videos": [
            {
                "title": "Highlights",
                "embed": "<div style='width:100%;height:0px;position:relative;padding-bottom:56.250%;'><iframe src='https:\/\/www.scorebat.com\/embed\/v\/5e5c27b21f86e\/?s=2' frameborder='0' width='100%' height='100%' allowfullscreen allow='autoplay; fullscreen' style='width:100%;height:100%;position:absolute;left:0px;top:0px;overflow:hidden;'><\/iframe><\/div>"
            }
        ]
    },
    {
        "title": "Cagliari - Roma",
        "embed": "<div style='width:75%;height:0px;position:relative;padding-bottom:56.250%;'><iframe src='https:\/\/www.scorebat.com\/embed\/v\/5e5c1d1782acc\/?s=2' frameborder='0' width='100%' height='100%' allowfullscreen allow='autoplay; fullscreen' style='width:100%;height:100%;position:absolute;left:0px;top:0px;overflow:hidden;'><\/iframe><\/div>",
        "url": "https:\/\/www.scorebat.com\/cagliari-vs-roma-live-stream\/",
        "thumbnail": "https:\/\/www.scorebat.com\/og\/m\/og865716.jpeg",
        "date": "2020-03-01T17:00:00+0000",
        "id": 21,
        "side1": {
            "name": "Cagliari",
            "url": "https:\/\/www.scorebat.com\/live-stream\/cagliari\/"
        },
        "side2": {
            "name": "Roma",
            "url": "https:\/\/www.scorebat.com\/live-stream\/roma\/"
        },
        "competition": {
            "name": "ITALY: Serie A",
            "id": 13,
            "url": "https:\/\/www.scorebat.com\/italy-serie-a-live-scores\/"
        },
        "videos": [
            {
                "title": "Highlights",
                "embed": "<div style='width:100%;height:0px;position:relative;padding-bottom:56.250%;'><iframe src='https:\/\/www.scorebat.com\/embed\/v\/5e5c1d1782acc\/?s=2' frameborder='0' width='100%' height='100%' allowfullscreen allow='autoplay; fullscreen' style='width:100%;height:100%;position:absolute;left:0px;top:0px;overflow:hidden;'><\/iframe><\/div>"
            }
        ]
    },
    {
        "title": "Watford - Liverpool",
        "embed": "<div style='width:75%;height:0px;position:relative;padding-bottom:56.250%;'><iframe src='https:\/\/www.scorebat.com\/embed\/v\/5e5c662041a51\/?s=2' frameborder='0' width='100%' height='100%' allowfullscreen allow='autoplay; fullscreen' style='width:100%;height:100%;position:absolute;left:0px;top:0px;overflow:hidden;'><\/iframe><\/div>",
        "url": "https:\/\/www.scorebat.com\/liverpool-vs-watford-live-stream\/",
        "thumbnail": "https:\/\/www.scorebat.com\/og\/m\/og821128.jpeg",
        "date": "2020-02-29T17:30:00+0000",
        "id": 23,
        "side1": {
            "name": "Watford",
            "url": "https:\/\/www.scorebat.com\/live-stream\/watford\/"
        },
        "side2": {
            "name": "Liverpool",
            "url": "https:\/\/www.scorebat.com\/live-stream\/liverpool\/"
        },
        "competition": {
            "name": "ENGLAND: Premier League",
            "id": 15,
            "url": "https:\/\/www.scorebat.com\/england-premier-league-live-scores\/"
        },
        "videos": [
            {
                "title": "Highlights",
                "embed": "<div style='width:100%;height:0px;position:relative;padding-bottom:56.250%;'><iframe src='https:\/\/www.scorebat.com\/embed\/v\/5e5c662041a51\/?s=2' frameborder='0' width='100%' height='100%' allowfullscreen allow='autoplay; fullscreen' style='width:100%;height:100%;position:absolute;left:0px;top:0px;overflow:hidden;'><\/iframe><\/div>"
            },
            {
                "title": "Highlights",
                "embed": "<div style='width:100%;height:0px;position:relative;padding-bottom:56.250%;'><iframe src='https:\/\/www.scorebat.com\/embed\/v\/5e5b0c2e3b6a4\/?s=2' frameborder='0' width='100%' height='100%' allowfullscreen allow='autoplay; fullscreen' style='width:100%;height:100%;position:absolute;left:0px;top:0px;overflow:hidden;'><\/iframe><\/div>"
            }
        ]
    },
    {
        "title": "Napoli - Torino",
        "embed": "<div style='width:75%;height:0px;position:relative;padding-bottom:56.250%;'><iframe src='https:\/\/www.scorebat.com\/embed\/v\/5e5b0bb6aef67\/?s=2' frameborder='0' width='100%' height='100%' allowfullscreen allow='autoplay; fullscreen' style='width:100%;height:100%;position:absolute;left:0px;top:0px;overflow:hidden;'><\/iframe><\/div>",
        "url": "https:\/\/www.scorebat.com\/napoli-vs-torino-live-stream\/",
        "thumbnail": "https:\/\/www.scorebat.com\/og\/m\/og865718.jpeg",
        "date": "2020-02-29T19:45:00+0000",
        "id": 24,
        "side1": {
            "name": "Napoli",
            "url": "https:\/\/www.scorebat.com\/live-stream\/napoli\/"
        },
        "side2": {
            "name": "Torino",
            "url": "https:\/\/www.scorebat.com\/live-stream\/torino\/"
        },
        "competition": {
            "name": "ITALY: Serie A",
            "id": 13,
            "url": "https:\/\/www.scorebat.com\/italy-serie-a-live-scores\/"
        },
        "videos": [
            {
                "title": "Highlights",
                "embed": "<div style='width:100%;height:0px;position:relative;padding-bottom:56.250%;'><iframe src='https:\/\/www.scorebat.com\/embed\/v\/5e5b0bb6aef67\/?s=2' frameborder='0' width='100%' height='100%' allowfullscreen allow='autoplay; fullscreen' style='width:100%;height:100%;position:absolute;left:0px;top:0px;overflow:hidden;'><\/iframe><\/div>"
            }
        ]
    },
    {
        "title": "Bournemouth - Chelsea",
        "embed": "<div style='width:75%;height:0px;position:relative;padding-bottom:56.250%;'><iframe src='https:\/\/www.scorebat.com\/embed\/v\/5e5ac81a5dc89\/?s=2' frameborder='0' width='100%' height='100%' allowfullscreen allow='autoplay; fullscreen' style='width:100%;height:100%;position:absolute;left:0px;top:0px;overflow:hidden;'><\/iframe><\/div>",
        "url": "https:\/\/www.scorebat.com\/bournemouth-vs-chelsea-live-stream\/",
        "thumbnail": "https:\/\/www.scorebat.com\/og\/m\/og821120.jpeg",
        "date": "2020-02-29T15:00:00+0000",
        "id": 25,
        "side1": {
            "name": "Bournemouth",
            "url": "https:\/\/www.scorebat.com\/live-stream\/bournemouth\/"
        },
        "side2": {
            "name": "Chelsea",
            "url": "https:\/\/www.scorebat.com\/live-stream\/chelsea\/"
        },
        "competition": {
            "name": "ENGLAND: Premier League",
            "id": 15,
            "url": "https:\/\/www.scorebat.com\/england-premier-league-live-scores\/"
        },
        "videos": [
            {
                "title": "Highlights",
                "embed": "<div style='width:100%;height:0px;position:relative;padding-bottom:56.250%;'><iframe src='https:\/\/www.scorebat.com\/embed\/v\/5e5ac81a5dc89\/?s=2' frameborder='0' width='100%' height='100%' allowfullscreen allow='autoplay; fullscreen' style='width:100%;height:100%;position:absolute;left:0px;top:0px;overflow:hidden;'><\/iframe><\/div>"
            }
        ]
    },
    {
        "title": "Real Madrid - Manchester City",
        "embed": "<div style='width:75%;height:0px;position:relative;padding-bottom:56.250%;'><iframe src='https:\/\/www.scorebat.com\/embed\/v\/5e5b0c50a6a20\/?s=2' frameborder='0' width='100%' height='100%' allowfullscreen allow='autoplay; fullscreen' style='width:100%;height:100%;position:absolute;left:0px;top:0px;overflow:hidden;'><\/iframe><\/div>",
        "url": "https:\/\/www.scorebat.com\/manchester-city-vs-real-madrid-live-stream\/",
        "thumbnail": "https:\/\/www.scorebat.com\/og\/m\/og903614.jpeg",
        "date": "2020-02-26T20:00:00+0000",
        "id": 27,
        "side1": {
            "name": "Real Madrid",
            "url": "https:\/\/www.scorebat.com\/live-stream\/real-madrid\/"
        },
        "side2": {
            "name": "Manchester City",
            "url": "https:\/\/www.scorebat.com\/live-stream\/manchester-city\/"
        },
        "competition": {
            "name": "CHAMPIONS LEAGUE: 1\/8 Final",
            "id": 503,
            "url": "https:\/\/www.scorebat.com\/champions-league-18-final-live-scores\/"
        },
        "videos": [
            {
                "title": "Highlights",
                "embed": "<div style='width:100%;height:0px;position:relative;padding-bottom:56.250%;'><iframe src='https:\/\/www.scorebat.com\/embed\/v\/5e5b0c50a6a20\/?s=2' frameborder='0' width='100%' height='100%' allowfullscreen allow='autoplay; fullscreen' style='width:100%;height:100%;position:absolute;left:0px;top:0px;overflow:hidden;'><\/iframe><\/div>"
            }
        ]
    },
    {
        "title": "Lyon - Juventus",
        "embed": "<div style='width:75%;height:0px;position:relative;padding-bottom:56.250%;'><iframe src='https:\/\/www.scorebat.com\/embed\/v\/5e8c42303e60a\/?s=2' frameborder='0' width='100%' height='100%' allowfullscreen allow='autoplay; fullscreen' style='width:100%;height:100%;position:absolute;left:0px;top:0px;overflow:hidden;'><\/iframe><\/div>",
        "url": "https:\/\/www.scorebat.com\/juventus-vs-lyon-live-stream\/",
        "thumbnail": "https:\/\/www.scorebat.com\/og\/m\/og903616.jpeg",
        "date": "2020-02-26T20:00:00+0000",
        "id": 28,
        "side1": {
            "name": "Lyon",
            "url": "https:\/\/www.scorebat.com\/live-stream\/lyon\/"
        },
        "side2": {
            "name": "Juventus",
            "url": "https:\/\/www.scorebat.com\/live-stream\/juventus\/"
        },
        "competition": {
            "name": "CHAMPIONS LEAGUE: 1\/8 Final",
            "id": 503,
            "url": "https:\/\/www.scorebat.com\/champions-league-18-final-live-scores\/"
        },
        "videos": [
            {
                "title": "1-0 Tousart",
                "embed": "<div style='width:100%;height:0px;position:relative;padding-bottom:56.250%;'><iframe src='https:\/\/www.scorebat.com\/embed\/v\/5e8c42303e60a\/?s=2' frameborder='0' width='100%' height='100%' allowfullscreen allow='autoplay; fullscreen' style='width:100%;height:100%;position:absolute;left:0px;top:0px;overflow:hidden;'><\/iframe><\/div>"
            }
        ]
    },
    {
        "title": "Chelsea - Bayern Munich",
        "embed": "<div style='width:75%;height:0px;position:relative;padding-bottom:56.250%;'><iframe src='https:\/\/www.scorebat.com\/embed\/v\/5e5cab9d706aa\/?s=2' frameborder='0' width='100%' height='100%' allowfullscreen allow='autoplay; fullscreen' style='width:100%;height:100%;position:absolute;left:0px;top:0px;overflow:hidden;'><\/iframe><\/div>",
        "url": "https:\/\/www.scorebat.com\/bayern-munich-vs-chelsea-live-stream\/",
        "thumbnail": "https:\/\/www.scorebat.com\/og\/m\/og903610.jpeg",
        "date": "2020-02-25T20:00:00+0000",
        "id": 29,
        "side1": {
            "name": "Chelsea",
            "url": "https:\/\/www.scorebat.com\/live-stream\/chelsea\/"
        },
        "side2": {
            "name": "Bayern Munich",
            "url": "https:\/\/www.scorebat.com\/live-stream\/bayern-munich\/"
        },
        "competition": {
            "name": "CHAMPIONS LEAGUE: 1\/8 Final",
            "id": 503,
            "url": "https:\/\/www.scorebat.com\/champions-league-18-final-live-scores\/"
        },
        "videos": [
            {
                "title": "Highlights",
                "embed": "<div style='width:100%;height:0px;position:relative;padding-bottom:56.250%;'><iframe src='https:\/\/www.scorebat.com\/embed\/v\/5e5cab9d706aa\/?s=2' frameborder='0' width='100%' height='100%' allowfullscreen allow='autoplay; fullscreen' style='width:100%;height:100%;position:absolute;left:0px;top:0px;overflow:hidden;'><\/iframe><\/div>"
            }
        ]
    },
    {
        "title": "Napoli - Barcelona",
        "embed": "<div style='width:75%;height:0px;position:relative;padding-bottom:56.250%;'><iframe src='https:\/\/www.scorebat.com\/embed\/v\/5e5cab011a95d\/?s=2' frameborder='0' width='100%' height='100%' allowfullscreen allow='autoplay; fullscreen' style='width:100%;height:100%;position:absolute;left:0px;top:0px;overflow:hidden;'><\/iframe><\/div>",
        "url": "https:\/\/www.scorebat.com\/barcelona-vs-napoli-live-stream\/",
        "thumbnail": "https:\/\/www.scorebat.com\/og\/m\/og903612.jpeg",
        "date": "2020-02-25T20:00:00+0000",
        "id": 30,
        "side1": {
            "name": "Napoli",
            "url": "https:\/\/www.scorebat.com\/live-stream\/napoli\/"
        },
        "side2": {
            "name": "Barcelona",
            "url": "https:\/\/www.scorebat.com\/live-stream\/barcelona\/"
        },
        "competition": {
            "name": "CHAMPIONS LEAGUE: 1\/8 Final",
            "id": 503,
            "url": "https:\/\/www.scorebat.com\/champions-league-18-final-live-scores\/"
        },
        "videos": [
            {
                "title": "Highlights",
                "embed": "<div style='width:100%;height:0px;position:relative;padding-bottom:56.250%;'><iframe src='https:\/\/www.scorebat.com\/embed\/v\/5e5cab011a95d\/?s=2' frameborder='0' width='100%' height='100%' allowfullscreen allow='autoplay; fullscreen' style='width:100%;height:100%;position:absolute;left:0px;top:0px;overflow:hidden;'><\/iframe><\/div>"
            }
        ]
    },
    {
        "title": "Liverpool - West Ham United",
        "embed": "<div style='width:75%;height:0px;position:relative;padding-bottom:56.250%;'><iframe src='https:\/\/www.scorebat.com\/embed\/v\/5e54713528f6d\/?s=2' frameborder='0' width='100%' height='100%' allowfullscreen allow='autoplay; fullscreen' style='width:100%;height:100%;position:absolute;left:0px;top:0px;overflow:hidden;'><\/iframe><\/div>",
        "url": "https:\/\/www.scorebat.com\/liverpool-vs-west-ham-united-live-stream\/",
        "thumbnail": "https:\/\/www.scorebat.com\/og\/m\/og821115.jpeg",
        "date": "2020-02-24T20:00:00+0000",
        "id": 31,
        "side1": {
            "name": "Liverpool",
            "url": "https:\/\/www.scorebat.com\/live-stream\/liverpool\/"
        },
        "side2": {
            "name": "West Ham United",
            "url": "https:\/\/www.scorebat.com\/live-stream\/west-ham-united\/"
        },
        "competition": {
            "name": "ENGLAND: Premier League",
            "id": 15,
            "url": "https:\/\/www.scorebat.com\/england-premier-league-live-scores\/"
        },
        "videos": [
            {
                "title": "Highlights",
                "embed": "<div style='width:100%;height:0px;position:relative;padding-bottom:56.250%;'><iframe src='https:\/\/www.scorebat.com\/embed\/v\/5e54713528f6d\/?s=2' frameborder='0' width='100%' height='100%' allowfullscreen allow='autoplay; fullscreen' style='width:100%;height:100%;position:absolute;left:0px;top:0px;overflow:hidden;'><\/iframe><\/div>"
            }
        ]
    },
    {
        "title": "Arsenal - Everton",
        "embed": "<div style='width:75%;height:0px;position:relative;padding-bottom:56.250%;'><iframe src='https:\/\/www.scorebat.com\/embed\/v\/5e54b18fd117e\/?s=2' frameborder='0' width='100%' height='100%' allowfullscreen allow='autoplay; fullscreen' style='width:100%;height:100%;position:absolute;left:0px;top:0px;overflow:hidden;'><\/iframe><\/div>",
        "url": "https:\/\/www.scorebat.com\/arsenal-vs-everton-live-stream\/",
        "thumbnail": "https:\/\/www.scorebat.com\/og\/m\/og821110.jpeg",
        "date": "2020-02-23T16:30:00+0000",
        "id": 32,
        "side1": {
            "name": "Arsenal",
            "url": "https:\/\/www.scorebat.com\/live-stream\/arsenal\/"
        },
        "side2": {
            "name": "Everton",
            "url": "https:\/\/www.scorebat.com\/live-stream\/everton\/"
        },
        "competition": {
            "name": "ENGLAND: Premier League",
            "id": 15,
            "url": "https:\/\/www.scorebat.com\/england-premier-league-live-scores\/"
        },
        "videos": [
            {
                "title": "Extended highlights",
                "embed": "<div style='width:100%;height:0px;position:relative;padding-bottom:56.250%;'><iframe src='https:\/\/www.scorebat.com\/embed\/v\/5e54b18fd117e\/?s=2' frameborder='0' width='100%' height='100%' allowfullscreen allow='autoplay; fullscreen' style='width:100%;height:100%;position:absolute;left:0px;top:0px;overflow:hidden;'><\/iframe><\/div>"
            },
            {
                "title": "Highlights",
                "embed": "<div style='width:100%;height:0px;position:relative;padding-bottom:56.250%;'><iframe src='https:\/\/www.scorebat.com\/embed\/v\/5e532620d5e42\/?s=2' frameborder='0' width='100%' height='100%' allowfullscreen allow='autoplay; fullscreen' style='width:100%;height:100%;position:absolute;left:0px;top:0px;overflow:hidden;'><\/iframe><\/div>"
            },
            {
                "title": "Highlights",
                "embed": "<div style='width:100%;height:0px;position:relative;padding-bottom:56.250%;'><iframe src='https:\/\/www.scorebat.com\/embed\/v\/5e52fe4944272\/?s=2' frameborder='0' width='100%' height='100%' allowfullscreen allow='autoplay; fullscreen' style='width:100%;height:100%;position:absolute;left:0px;top:0px;overflow:hidden;'><\/iframe><\/div>"
            }
        ]
    },
    {
        "title": "Manchester United - Watford",
        "embed": "<div style='width:75%;height:0px;position:relative;padding-bottom:56.250%;'><iframe src='https:\/\/www.scorebat.com\/embed\/v\/5e54b17843bec\/?s=2' frameborder='0' width='100%' height='100%' allowfullscreen allow='autoplay; fullscreen' style='width:100%;height:100%;position:absolute;left:0px;top:0px;overflow:hidden;'><\/iframe><\/div>",
        "url": "https:\/\/www.scorebat.com\/manchester-united-vs-watford-live-stream\/",
        "thumbnail": "https:\/\/www.scorebat.com\/og\/m\/og821116.jpeg",
        "date": "2020-02-23T14:00:00+0000",
        "id": 33,
        "side1": {
            "name": "Manchester United",
            "url": "https:\/\/www.scorebat.com\/live-stream\/manchester-united\/"
        },
        "side2": {
            "name": "Watford",
            "url": "https:\/\/www.scorebat.com\/live-stream\/watford\/"
        },
        "competition": {
            "name": "ENGLAND: Premier League",
            "id": 15,
            "url": "https:\/\/www.scorebat.com\/england-premier-league-live-scores\/"
        },
        "videos": [
            {
                "title": "Extended Highlights",
                "embed": "<div style='width:100%;height:0px;position:relative;padding-bottom:56.250%;'><iframe src='https:\/\/www.scorebat.com\/embed\/v\/5e54b17843bec\/?s=2' frameborder='0' width='100%' height='100%' allowfullscreen allow='autoplay; fullscreen' style='width:100%;height:100%;position:absolute;left:0px;top:0px;overflow:hidden;'><\/iframe><\/div>"
            },
            {
                "title": "Highlights",
                "embed": "<div style='width:100%;height:0px;position:relative;padding-bottom:56.250%;'><iframe src='https:\/\/www.scorebat.com\/embed\/v\/5e53acafa8b3d\/?s=2' frameborder='0' width='100%' height='100%' allowfullscreen allow='autoplay; fullscreen' style='width:100%;height:100%;position:absolute;left:0px;top:0px;overflow:hidden;'><\/iframe><\/div>"
            },
            {
                "title": "Highlights",
                "embed": "<div style='width:100%;height:0px;position:relative;padding-bottom:56.250%;'><iframe src='https:\/\/www.scorebat.com\/embed\/v\/5e5325fb1512b\/?s=2' frameborder='0' width='100%' height='100%' allowfullscreen allow='autoplay; fullscreen' style='width:100%;height:100%;position:absolute;left:0px;top:0px;overflow:hidden;'><\/iframe><\/div>"
            }
        ]
    },
    {
        "title": "Roma - Lecce",
        "embed": "<div style='width:75%;height:0px;position:relative;padding-bottom:56.250%;'><iframe src='https:\/\/www.scorebat.com\/embed\/v\/5e52dcc001a85\/?s=2' frameborder='0' width='100%' height='100%' allowfullscreen allow='autoplay; fullscreen' style='width:100%;height:100%;position:absolute;left:0px;top:0px;overflow:hidden;'><\/iframe><\/div>",
        "url": "https:\/\/www.scorebat.com\/lecce-vs-roma-live-stream\/",
        "thumbnail": "https:\/\/www.scorebat.com\/og\/m\/og865702.jpeg",
        "date": "2020-02-23T17:00:00+0000",
        "id": 34,
        "side1": {
            "name": "Roma",
            "url": "https:\/\/www.scorebat.com\/live-stream\/roma\/"
        },
        "side2": {
            "name": "Lecce",
            "url": "https:\/\/www.scorebat.com\/live-stream\/lecce\/"
        },
        "competition": {
            "name": "ITALY: Serie A",
            "id": 13,
            "url": "https:\/\/www.scorebat.com\/italy-serie-a-live-scores\/"
        },
        "videos": [
            {
                "title": "Highlights",
                "embed": "<div style='width:100%;height:0px;position:relative;padding-bottom:56.250%;'><iframe src='https:\/\/www.scorebat.com\/embed\/v\/5e52dcc001a85\/?s=2' frameborder='0' width='100%' height='100%' allowfullscreen allow='autoplay; fullscreen' style='width:100%;height:100%;position:absolute;left:0px;top:0px;overflow:hidden;'><\/iframe><\/div>"
            }
        ]
    },
    {
        "title": "Fiorentina - AC Milan",
        "embed": "<div style='width:75%;height:0px;position:relative;padding-bottom:56.250%;'><iframe src='https:\/\/www.scorebat.com\/embed\/v\/5e51ade0d5520\/?s=2' frameborder='0' width='100%' height='100%' allowfullscreen allow='autoplay; fullscreen' style='width:100%;height:100%;position:absolute;left:0px;top:0px;overflow:hidden;'><\/iframe><\/div>",
        "url": "https:\/\/www.scorebat.com\/ac-milan-vs-fiorentina-live-stream\/",
        "thumbnail": "https:\/\/www.scorebat.com\/og\/m\/og865703.jpeg",
        "date": "2020-02-22T19:45:00+0000",
        "id": 38,
        "side1": {
            "name": "Fiorentina",
            "url": "https:\/\/www.scorebat.com\/live-stream\/fiorentina\/"
        },
        "side2": {
            "name": "AC Milan",
            "url": "https:\/\/www.scorebat.com\/live-stream\/ac-milan\/"
        },
        "competition": {
            "name": "ITALY: Serie A",
            "id": 13,
            "url": "https:\/\/www.scorebat.com\/italy-serie-a-live-scores\/"
        },
        "videos": [
            {
                "title": "Highlights",
                "embed": "<div style='width:100%;height:0px;position:relative;padding-bottom:56.250%;'><iframe src='https:\/\/www.scorebat.com\/embed\/v\/5e51ade0d5520\/?s=2' frameborder='0' width='100%' height='100%' allowfullscreen allow='autoplay; fullscreen' style='width:100%;height:100%;position:absolute;left:0px;top:0px;overflow:hidden;'><\/iframe><\/div>"
            }
        ]
    },
    {
        "title": "Leicester City - Manchester City",
        "embed": "<div style='width:75%;height:0px;position:relative;padding-bottom:56.250%;'><iframe src='https:\/\/www.scorebat.com\/embed\/v\/5e51a702b7308\/?s=2' frameborder='0' width='100%' height='100%' allowfullscreen allow='autoplay; fullscreen' style='width:100%;height:100%;position:absolute;left:0px;top:0px;overflow:hidden;'><\/iframe><\/div>",
        "url": "https:\/\/www.scorebat.com\/leicester-city-vs-manchester-city-live-stream\/",
        "thumbnail": "https:\/\/www.scorebat.com\/og\/m\/og821114.jpeg",
        "date": "2020-02-22T17:30:00+0000",
        "id": 39,
        "side1": {
            "name": "Leicester City",
            "url": "https:\/\/www.scorebat.com\/live-stream\/leicester-city\/"
        },
        "side2": {
            "name": "Manchester City",
            "url": "https:\/\/www.scorebat.com\/live-stream\/manchester-city\/"
        },
        "competition": {
            "name": "ENGLAND: Premier League",
            "id": 15,
            "url": "https:\/\/www.scorebat.com\/england-premier-league-live-scores\/"
        },
        "videos": [
            {
                "title": "Highlights",
                "embed": "<div style='width:100%;height:0px;position:relative;padding-bottom:56.250%;'><iframe src='https:\/\/www.scorebat.com\/embed\/v\/5e51a702b7308\/?s=2' frameborder='0' width='100%' height='100%' allowfullscreen allow='autoplay; fullscreen' style='width:100%;height:100%;position:absolute;left:0px;top:0px;overflow:hidden;'><\/iframe><\/div>"
            }
        ]
    },
    {
        "title": "Spal - Juventus",
        "embed": "<div style='width:75%;height:0px;position:relative;padding-bottom:56.250%;'><iframe src='https:\/\/www.scorebat.com\/embed\/v\/5e518ea5b3350\/?s=2' frameborder='0' width='100%' height='100%' allowfullscreen allow='autoplay; fullscreen' style='width:100%;height:100%;position:absolute;left:0px;top:0px;overflow:hidden;'><\/iframe><\/div>",
        "url": "https:\/\/www.scorebat.com\/juventus-vs-spal-live-stream\/",
        "thumbnail": "https:\/\/www.scorebat.com\/og\/m\/og865700.jpeg",
        "date": "2020-02-22T17:00:00+0000",
        "id": 40,
        "side1": {
            "name": "Spal",
            "url": "https:\/\/www.scorebat.com\/live-stream\/spal\/"
        },
        "side2": {
            "name": "Juventus",
            "url": "https:\/\/www.scorebat.com\/live-stream\/juventus\/"
        },
        "competition": {
            "name": "ITALY: Serie A",
            "id": 13,
            "url": "https:\/\/www.scorebat.com\/italy-serie-a-live-scores\/"
        },
        "videos": [
            {
                "title": "Highlights",
                "embed": "<div style='width:100%;height:0px;position:relative;padding-bottom:56.250%;'><iframe src='https:\/\/www.scorebat.com\/embed\/v\/5e518ea5b3350\/?s=2' frameborder='0' width='100%' height='100%' allowfullscreen allow='autoplay; fullscreen' style='width:100%;height:100%;position:absolute;left:0px;top:0px;overflow:hidden;'><\/iframe><\/div>"
            }
        ]
    }
]